{"meta":{"type":"db","canSave":false,"canEdit":true,"canAdmin":false,"canStar":false,"canDelete":false,"slug":"annotations","url":"/d/000000010/annotations","expires":"0001-01-01T00:00:00Z","created":"2018-01-08T03:46:09Z","updated":"2022-12-09T09:52:33Z","updatedBy":"torkel@grafana.com","createdBy":"torkel.odegaard@gmail.com","version":39,"hasAcl":false,"isFolder":false,"folderId":608,"folderUid":"PGJ1Fr4Zz","folderTitle":"Demos","folderUrl":"/dashboards/f/PGJ1Fr4Zz/demos","provisioned":false,"provisionedExternalId":"","annotationsPermissions":{"dashboard":{"canAdd":true,"canEdit":true,"canDelete":true},"organization":{"canAdd":false,"canEdit":false,"canDelete":false}},"hasPublicDashboard":false,"publicDashboardAccessToken":"","publicDashboardUid":"","publicDashboardEnabled":false},"dashboard":{"annotations":{"enable":true,"list":[{"builtIn":1,"datasource":{"type":"datasource","uid":"grafana"},"enable":true,"hide":true,"iconColor":"rgba(0, 211, 255, 1)","name":"Annotations \u0026 Alerts","target":{"limit":100,"matchAny":false,"tags":[],"type":"dashboard"},"type":"dashboard"},{"datasource":{"type":"datasource","uid":"grafana"},"enable":true,"hide":false,"iconColor":"rgba(255, 96, 96, 1)","limit":100,"name":"deploys","showIn":0,"tags":["deploy"],"target":{"limit":100,"matchAny":false,"tags":["deploy"],"type":"tags"},"type":"tags"},{"datasource":{"type":"datasource","uid":"grafana"},"enable":false,"hide":false,"iconColor":"rgba(255, 96, 96, 1)","limit":100,"name":"outages","showIn":0,"tags":["outage"],"type":"tags"},{"datasource":{"type":"graphite","uid":"000000001"},"enable":false,"hide":false,"iconColor":"rgba(255, 96, 96, 1)","limit":100,"name":"updates","showIn":0,"tags":[],"target":{"fromAnnotations":true,"target":"statsd.fakesite.counters.session_start.tablet.count","textEditor":true},"type":"tags"}]},"editable":true,"fiscalYearStartMonth":0,"graphTooltip":0,"id":10,"links":[],"liveNow":false,"panels":[{"aliasColors":{"web_server_01":"#7EB26D","web_server_02":"#B7DBAB"},"annotate":{"enable":false},"bars":false,"dashLength":10,"dashes":false,"datasource":{"type":"graphite","uid":"000000001"},"editable":true,"fieldConfig":{"defaults":{"links":[]},"overrides":[]},"fill":1,"fillGradient":0,"grid":{"min":0},"gridPos":{"h":11,"w":24,"x":0,"y":0},"hiddenSeries":false,"id":1,"interactive":true,"legend":{"avg":false,"current":false,"max":false,"min":false,"show":true,"total":false,"values":false},"legend_counts":true,"lines":true,"linewidth":1,"links":[],"nullPointMode":"connected","options":{"alertThreshold":true},"percentage":false,"pluginVersion":"9.3.2-45041","pointradius":5,"points":false,"renderer":"flot","resolution":100,"scale":1,"seriesOverrides":[],"spaceLength":10,"spyable":true,"stack":true,"steppedLine":false,"targets":[{"refId":"A","target":"aliasByNode(apps.fakesite.web_server_02.counters.requests.count,2)"},{"refId":"B","target":"aliasByNode(scale(apps.fakesite.web_server_01.counters.requests.count, 2), 2)"},{"refId":"C","target":"aliasByNode(scale(apps.fakesite.web_server_03.counters.requests.count, 4), 2)"}],"thresholds":[],"timeRegions":[],"timezone":"browser","title":"QPS webfronts","tooltip":{"msResolution":false,"query_as_alias":true,"shared":false,"sort":0,"value_type":"cumulative"},"type":"graph","xaxis":{"mode":"time","show":true,"values":[]},"yaxes":[{"format":"short","logBase":1,"show":true},{"format":"short","logBase":1,"show":true}],"yaxis":{"align":false},"zerofill":true},{"aliasColors":{"web_server_01":"#1F78C1","web_server_02":"#6ED0E0"},"annotate":{"enable":false},"bars":false,"dashLength":10,"dashes":false,"datasource":{"type":"graphite","uid":"000000001"},"editable":true,"fieldConfig":{"defaults":{"links":[]},"overrides":[]},"fill":0,"fillGradient":0,"grid":{"min":0},"gridPos":{"h":9,"w":12,"x":0,"y":11},"hiddenSeries":false,"id":2,"interactive":true,"legend":{"avg":false,"current":false,"max":false,"min":false,"show":true,"total":false,"values":false},"legend_counts":true,"lines":true,"linewidth":2,"nullPointMode":"connected","options":{"alertThreshold":true},"percentage":false,"pluginVersion":"9.3.2-45041","pointradius":5,"points":false,"renderer":"flot","resolution":100,"scale":1,"seriesOverrides":[],"spaceLength":10,"spyable":true,"stack":true,"steppedLine":false,"targets":[{"refId":"A","target":"aliasByNode(movingAverage(apps.fakesite.web_server_02.counters.request_status.code_304.count, 6), 2)"}],"thresholds":[],"timeRegions":[],"timezone":"browser","title":"Annotations example","tooltip":{"msResolution":false,"query_as_alias":true,"shared":false,"sort":0,"value_type":"cumulative"},"type":"graph","xaxis":{"mode":"time","show":true,"values":[]},"yaxes":[{"format":"short","logBase":1,"show":true},{"format":"short","logBase":1,"show":true}],"yaxis":{"align":false},"zerofill":true},{"aliasColors":{"web_server_01":"#1F78C1","web_server_02":"#CCA300"},"annotate":{"enable":false},"bars":false,"dashLength":10,"dashes":false,"datasource":{"type":"graphite","uid":"000000001"},"editable":true,"fieldConfig":{"defaults":{"links":[]},"overrides":[]},"fill":0,"fillGradient":0,"grid":{"min":0},"gridPos":{"h":9,"w":12,"x":12,"y":11},"hiddenSeries":false,"id":3,"interactive":true,"legend":{"avg":false,"current":false,"max":false,"min":false,"show":true,"total":false,"values":false},"legend_counts":true,"lines":true,"linewidth":2,"nullPointMode":"connected","options":{"alertThreshold":true},"percentage":false,"pluginVersion":"9.3.2-45041","pointradius":5,"points":false,"renderer":"flot","resolution":100,"scale":1,"seriesOverrides":[],"spaceLength":10,"spyable":true,"stack":true,"steppedLine":false,"targets":[{"refId":"A","target":"aliasByNode(movingAverage(apps.fakesite.web_server_02.counters.request_status.code_304.count, 6), 2)"}],"thresholds":[],"timeRegions":[],"timezone":"browser","title":"Annotations example","tooltip":{"msResolution":false,"query_as_alias":true,"shared":false,"sort":0,"value_type":"cumulative"},"type":"graph","xaxis":{"mode":"time","show":true,"values":[]},"yaxes":[{"format":"short","logBase":1,"show":true},{"format":"short","logBase":1,"show":true}],"yaxis":{"align":false},"zerofill":true},{"datasource":{"type":"dashboard","uid":"-- Dashboard --"},"gridPos":{"h":7,"w":24,"x":0,"y":20},"id":4,"links":[],"options":{"limit":10,"navigateAfter":"10m","navigateBefore":"10m","navigateToPanel":true,"onlyFromThisDashboard":false,"onlyInTimeRange":false,"showTags":true,"showTime":true,"showUser":true},"pluginVersion":"v1.0","targets":[{"datasource":{"type":"datasource","uid":"-- Dashboard --"},"refId":"A"}],"title":"Annotations","transformations":[],"type":"annolist"}],"refresh":false,"schemaVersion":37,"style":"dark","tags":["annotations","demo","presentation"],"templating":{"list":[]},"time":{"from":"now-15m","to":"now"},"timepicker":{"collapse":false,"enable":true,"notice":false,"now":true,"refresh_intervals":["5s","10s","30s","1m","5m","15m","30m","1h","2h","1d"],"status":"Stable","time_options":["5m","15m","1h","6h","12h","24h","2d","7d","30d"],"type":"timepicker"},"timezone":"browser","title":"Annotations","uid":"000000010","version":39,"weekStart":""}}