{"meta":{"type":"db","canSave":false,"canEdit":true,"canAdmin":false,"canStar":false,"canDelete":false,"slug":"46995","url":"/d/9BWltAd4k/46995","expires":"0001-01-01T00:00:00Z","created":"2022-11-21T18:00:06Z","updated":"2022-11-21T18:00:06Z","updatedBy":"matt.abrams@grafana.com","createdBy":"matt.abrams@grafana.com","version":1,"hasAcl":false,"isFolder":false,"folderId":1113,"folderUid":"8OticeRnk","folderTitle":"Replicating issues","folderUrl":"/dashboards/f/8OticeRnk/replicating-issues","provisioned":false,"provisionedExternalId":"","annotationsPermissions":{"dashboard":{"canAdd":true,"canEdit":true,"canDelete":true},"organization":{"canAdd":false,"canEdit":false,"canDelete":false}},"hasPublicDashboard":false,"publicDashboardAccessToken":"","publicDashboardUid":"","publicDashboardEnabled":false},"dashboard":{"annotations":{"list":[{"builtIn":1,"datasource":{"type":"grafana","uid":"-- Grafana --"},"enable":true,"hide":true,"iconColor":"rgba(0, 211, 255, 1)","name":"Annotations \u0026 Alerts","target":{"limit":100,"matchAny":false,"tags":[],"type":"dashboard"},"type":"dashboard"}]},"editable":true,"fiscalYearStartMonth":0,"graphTooltip":0,"id":1751,"links":[],"liveNow":false,"panels":[{"datasource":{"type":"mysql","uid":"QTzGEw97z"},"fieldConfig":{"defaults":{"color":{"mode":"palette-classic"},"custom":{"axisCenteredZero":false,"axisColorMode":"text","axisLabel":"","axisPlacement":"auto","barAlignment":0,"drawStyle":"line","fillOpacity":0,"gradientMode":"none","hideFrom":{"legend":false,"tooltip":false,"viz":false},"lineInterpolation":"linear","lineWidth":1,"pointSize":5,"scaleDistribution":{"type":"linear"},"showPoints":"auto","spanNulls":false,"stacking":{"group":"A","mode":"none"},"thresholdsStyle":{"mode":"off"}},"mappings":[],"thresholds":{"mode":"absolute","steps":[{"color":"green","value":null},{"color":"red","value":80}]}},"overrides":[]},"gridPos":{"h":9,"w":12,"x":0,"y":0},"id":2,"options":{"legend":{"calcs":[],"displayMode":"list","placement":"bottom","showLegend":true},"tooltip":{"mode":"single","sort":"none"}},"targets":[{"datasource":{"type":"mysql","uid":"QTzGEw97z"},"refId":"A"}],"title":"Panel Title","type":"timeseries"}],"schemaVersion":37,"style":"dark","tags":[],"templating":{"list":[{"current":{"selected":true,"text":["1"],"value":["1"]},"datasource":{"type":"mysql","uid":"QTzGEw97z"},"definition":"SELECT 1;","description":"one","hide":0,"includeAll":true,"label":"one","multi":true,"name":"one","options":[],"query":"SELECT 1;","refresh":1,"regex":"","skipUrlSync":false,"sort":0,"type":"query"},{"current":{"selected":true,"text":["2"],"value":["2"]},"datasource":{"type":"mysql","uid":"QTzGEw97z"},"definition":"SELECT 2;","description":"two","hide":0,"includeAll":true,"label":"two","multi":true,"name":"two","options":[],"query":"SELECT 2;","refresh":1,"regex":"","skipUrlSync":false,"sort":0,"type":"query"}]},"time":{"from":"now-6h","to":"now"},"timepicker":{},"timezone":"","title":"#46995","uid":"9BWltAd4k","version":1,"weekStart":""}}