{"meta":{"type":"db","canSave":false,"canEdit":true,"canAdmin":false,"canStar":false,"canDelete":false,"slug":"45560","url":"/d/AhWVxxBnz/45560","expires":"0001-01-01T00:00:00Z","created":"2022-02-22T04:09:42Z","updated":"2022-02-22T04:09:59Z","updatedBy":"matt.abrams@grafana.com","createdBy":"matt.abrams@grafana.com","version":2,"hasAcl":false,"isFolder":false,"folderId":199,"folderUid":"NUrBVPWmz","folderTitle":"zTest","folderUrl":"/dashboards/f/NUrBVPWmz/ztest","provisioned":false,"provisionedExternalId":"","annotationsPermissions":{"dashboard":{"canAdd":true,"canEdit":true,"canDelete":true},"organization":{"canAdd":false,"canEdit":false,"canDelete":false}},"hasPublicDashboard":false,"publicDashboardAccessToken":"","publicDashboardUid":"","publicDashboardEnabled":false},"dashboard":{"annotations":{"list":[{"builtIn":1,"datasource":"-- Grafana --","enable":true,"hide":true,"iconColor":"rgba(0, 211, 255, 1)","name":"Annotations \u0026 Alerts","target":{"limit":100,"matchAny":false,"tags":[],"type":"dashboard"},"type":"dashboard"}]},"editable":true,"fiscalYearStartMonth":0,"graphTooltip":0,"id":1384,"links":[],"liveNow":false,"panels":[{"datasource":{"type":"marcusolsson-static-datasource","uid":"j_w3s5fMk"},"fieldConfig":{"defaults":{"color":{"mode":"palette-classic"},"custom":{"axisLabel":"","axisPlacement":"auto","barAlignment":0,"drawStyle":"line","fillOpacity":0,"gradientMode":"none","hideFrom":{"legend":false,"tooltip":false,"viz":false},"lineInterpolation":"linear","lineWidth":1,"pointSize":5,"scaleDistribution":{"type":"linear"},"showPoints":"auto","spanNulls":false,"stacking":{"group":"A","mode":"none"},"thresholdsStyle":{"mode":"off"}},"mappings":[],"thresholds":{"mode":"absolute","steps":[{"color":"green","value":null},{"color":"red","value":80}]}},"overrides":[]},"gridPos":{"h":9,"w":12,"x":0,"y":0},"id":2,"options":{"legend":{"calcs":[],"displayMode":"list","placement":"bottom"},"tooltip":{"mode":"multi","sort":"none"}},"pluginVersion":"8.4.1","targets":[{"datasource":{"type":"marcusolsson-static-datasource","uid":"j_w3s5fMk"},"frame":{"fields":[{"config":{},"name":"time","type":"time","values":[1645502646383,1645502649269,1645502743632]},{"config":{},"name":"countries","type":"number","values":[5,5,9]}],"meta":{"preferredVisualisationType":"graph"},"name":"foo-1"},"refId":"A"},{"datasource":{"type":"marcusolsson-static-datasource","uid":"j_w3s5fMk"},"frame":{"fields":[{"config":{},"name":"time","type":"time","values":[1645502646383,1645502647946,1645502649269,1645502743632]},{"config":{},"name":"countries","type":"number","values":[5,6,5,9]}],"meta":{"preferredVisualisationType":"graph"},"name":"foo-2"},"hide":false,"refId":"B"}],"title":"Panel Title","type":"timeseries"}],"refresh":false,"schemaVersion":35,"style":"dark","tags":[],"templating":{"list":[]},"time":{"from":"2022-02-22T04:03:57.567Z","to":"2022-02-22T04:06:01.726Z"},"timepicker":{},"timezone":"","title":"45560","uid":"AhWVxxBnz","version":2,"weekStart":""}}