{"meta":{"type":"db","canSave":false,"canEdit":true,"canAdmin":false,"canStar":false,"canDelete":false,"slug":"template-variable-formatting-options","url":"/d/cJtIfcWiz/template-variable-formatting-options","expires":"0001-01-01T00:00:00Z","created":"2018-04-17T09:21:05Z","updated":"2020-08-20T20:33:06Z","updatedBy":"diana.payton@grafana.com","createdBy":"dan.limerick@gmail.com","version":10,"hasAcl":false,"isFolder":false,"folderId":608,"folderUid":"PGJ1Fr4Zz","folderTitle":"Demos","folderUrl":"/dashboards/f/PGJ1Fr4Zz/demos","provisioned":false,"provisionedExternalId":"","annotationsPermissions":{"dashboard":{"canAdd":true,"canEdit":true,"canDelete":true},"organization":{"canAdd":false,"canEdit":false,"canDelete":false}},"hasPublicDashboard":false,"publicDashboardAccessToken":"","publicDashboardUid":"","publicDashboardEnabled":false},"dashboard":{"annotations":{"list":[{"$$hashKey":"object:10","builtIn":1,"datasource":"-- Grafana --","enable":true,"hide":true,"iconColor":"rgba(0, 211, 255, 1)","name":"Annotations \u0026 Alerts","type":"dashboard"}]},"editable":true,"gnetId":null,"graphTooltip":0,"id":195,"iteration":1587488382519,"links":[],"panels":[{"content":"# Template Variable Formatting Options\n\nSyntax: `${var_name:option}`\n\nChange the `servers` variable above to test the interpolation for the different formatting options in the table below. \n\n[Docs for Variables.](http://docs.grafana.org/reference/templating/)\n\n## Live Examples\n\nFilter Option | Example | Interpolated | Description\n------------ | ------------- | ------------- | -------------\n`glob` | `${var_name:glob}` | ${servers:glob} | (Default) Formats multi-value variable into a glob (for Graphite queries)\n`regex` | `${var_name:regex}` | ${servers:regex} | Formats multi-value variable into a regex string\n`pipe` | `${var_name:pipe}` | ${servers:pipe} | Formats multi-value variable into a pipe-separated string\n`csv`| `${var_name:csv}` | ${servers:csv} | Formats multi-value variable into a comma-separated string\n`distributed`| `${var_name:distributed}` | ${servers:distributed} | Formats multi-value variable in custom format for OpenTSDB.\n`lucene`| `${var_name:lucene}` | ${servers:lucene} | Formats multi-value variable as lucene expression\n`raw` |  `${var_name:raw}` | ${servers:raw} | Turns off data source specific formatting (like single quotes in an SQL query)\n","datasource":null,"gridPos":{"h":17,"w":17,"x":0,"y":0},"id":4,"links":[],"mode":"markdown","title":"Variable Formatting","type":"text"}],"schemaVersion":22,"style":"dark","tags":["templating","templated"],"templating":{"list":[{"allValue":null,"current":{"tags":[],"text":"test.1 + test2","value":["test.1","test2"]},"hide":0,"includeAll":true,"label":null,"multi":true,"name":"servers","options":[{"selected":false,"text":"All","value":"$__all"},{"selected":true,"text":"test.1","value":"test.1"},{"selected":true,"text":"test2","value":"test2"},{"selected":false,"text":"test3","value":"test3"}],"query":"test.1,test2,test3","skipUrlSync":false,"type":"custom"}]},"time":{"from":"now-6h","to":"now"},"timepicker":{"refresh_intervals":["5s","10s","30s","1m","5m","15m","30m","1h","2h","1d"],"time_options":["5m","15m","1h","6h","12h","24h","2d","7d","30d"]},"timezone":"","title":"Template Variable Formatting Options","uid":"cJtIfcWiz","variables":{"list":[]},"version":10}}