{"meta":{"type":"db","canSave":false,"canEdit":true,"canAdmin":false,"canStar":false,"canDelete":false,"slug":"test-delta-and-difference-in-legend-table","url":"/d/GkG2ftnnz/test-delta-and-difference-in-legend-table","expires":"0001-01-01T00:00:00Z","created":"2021-08-17T20:17:22Z","updated":"2021-08-17T20:17:22Z","updatedBy":"matt.abrams@grafana.com","createdBy":"matt.abrams@grafana.com","version":1,"hasAcl":false,"isFolder":false,"folderId":199,"folderUid":"NUrBVPWmz","folderTitle":"zTest","folderUrl":"/dashboards/f/NUrBVPWmz/ztest","provisioned":false,"provisionedExternalId":"","annotationsPermissions":{"dashboard":{"canAdd":true,"canEdit":true,"canDelete":true},"organization":{"canAdd":false,"canEdit":false,"canDelete":false}},"hasPublicDashboard":false,"publicDashboardAccessToken":"","publicDashboardUid":"","publicDashboardEnabled":false},"dashboard":{"annotations":{"list":[{"builtIn":1,"datasource":"-- Grafana --","enable":true,"hide":true,"iconColor":"rgba(0, 211, 255, 1)","name":"Annotations \u0026 Alerts","target":{"limit":100,"matchAny":false,"tags":[],"type":"dashboard"},"type":"dashboard"}]},"editable":true,"gnetId":null,"graphTooltip":0,"hideControls":false,"id":1173,"links":[],"panels":[{"datasource":"Grafana TestData","fieldConfig":{"defaults":{"color":{"mode":"palette-classic"},"custom":{"axisLabel":"","axisPlacement":"auto","barAlignment":0,"drawStyle":"line","fillOpacity":0,"gradientMode":"none","hideFrom":{"legend":false,"tooltip":false,"viz":false},"lineInterpolation":"linear","lineWidth":1,"pointSize":5,"scaleDistribution":{"type":"linear"},"showPoints":"auto","spanNulls":false,"stacking":{"group":"A","mode":"none"},"thresholdsStyle":{"mode":"off"}},"mappings":[],"thresholds":{"mode":"absolute","steps":[{"color":"green","value":null},{"color":"red","value":80}]}},"overrides":[]},"gridPos":{"h":10,"w":14,"x":0,"y":0},"id":6,"options":{"legend":{"calcs":["first","last","delta","diff"],"displayMode":"table","placement":"bottom"},"tooltip":{"mode":"single"}},"targets":[{"refId":"A","scenarioId":"csv_metric_values","stringInput":"1,6"},{"hide":false,"refId":"B","scenarioId":"csv_metric_values","stringInput":"6,1"},{"hide":false,"refId":"C","scenarioId":"csv_metric_values","stringInput":"6,-6"},{"hide":false,"refId":"D","scenarioId":"csv_metric_values","stringInput":"-6,6"}],"title":"Panel Title","type":"timeseries"},{"datasource":"Grafana TestData","fieldConfig":{"defaults":{"color":{"mode":"thresholds"},"custom":{"align":"auto","displayMode":"auto"},"mappings":[],"thresholds":{"mode":"absolute","steps":[{"color":"green","value":null},{"color":"red","value":80}]}},"overrides":[]},"gridPos":{"h":4,"w":14,"x":0,"y":10},"id":3,"options":{"showHeader":true},"pluginVersion":"8.1.0","targets":[{"csvContent":"first,last\n1,6\n6,1\n6,-6\n-6,6\n","refId":"A","scenarioId":"csv_content"}],"title":"Panel Title","transformations":[{"id":"calculateField","options":{"mode":"reduceRow","reduce":{"reducer":"delta"}}},{"id":"calculateField","options":{"mode":"reduceRow","reduce":{"reducer":"diff"}}}],"type":"table"},{"datasource":"Grafana TestData","fieldConfig":{"defaults":{"color":{"mode":"thresholds"},"custom":{"align":"auto","displayMode":"auto"},"mappings":[],"thresholds":{"mode":"absolute","steps":[{"color":"green","value":null},{"color":"red","value":80}]}},"overrides":[]},"gridPos":{"h":6,"w":14,"x":0,"y":14},"id":2,"options":{"showHeader":true},"pluginVersion":"8.1.0","targets":[{"csvContent":"first,second,third,fourth,fifth,last\n1,1,1,1,1,6\n1,1,1,1,7,6\n6,1,1,1,1,1\n6,1,1,1,7,1","refId":"A","scenarioId":"csv_content"}],"title":"Panel Title","transformations":[{"id":"calculateField","options":{"mode":"reduceRow","reduce":{"reducer":"delta"}}},{"id":"calculateField","options":{"mode":"reduceRow","reduce":{"reducer":"diff"}}}],"type":"table"},{"datasource":"Grafana TestData","fieldConfig":{"defaults":{"color":{"mode":"thresholds"},"custom":{"align":"auto","displayMode":"auto"},"mappings":[],"thresholds":{"mode":"absolute","steps":[{"color":"green","value":null},{"color":"red","value":80}]}},"overrides":[]},"gridPos":{"h":4,"w":14,"x":0,"y":20},"id":4,"options":{"showHeader":true},"pluginVersion":"8.1.0","targets":[{"csvContent":"first,second,last\n1,7,6\n6,7,1\n","refId":"A","scenarioId":"csv_content"}],"title":"Panel Title","transformations":[{"id":"calculateField","options":{"mode":"reduceRow","reduce":{"reducer":"delta"}}},{"id":"calculateField","options":{"mode":"reduceRow","reduce":{"reducer":"diff"}}}],"type":"table"}],"schemaVersion":30,"style":"dark","tags":[],"templating":{"list":[]},"time":{"from":"now-6h","to":"now"},"timepicker":{},"timezone":"","title":"test-delta and difference in legend + table","uid":"GkG2ftnnz","version":1}}