{"meta":{"type":"db","canSave":false,"canEdit":true,"canAdmin":false,"canStar":false,"canDelete":false,"slug":"elasticsearch-metrics-copy","url":"/d/HpOzpLpMz/elasticsearch-metrics-copy","expires":"0001-01-01T00:00:00Z","created":"2020-10-26T14:25:15Z","updated":"2020-10-26T14:25:15Z","updatedBy":"torkel.odegaard@gmail.com","createdBy":"torkel.odegaard@gmail.com","version":1,"hasAcl":false,"isFolder":false,"folderId":199,"folderUid":"NUrBVPWmz","folderTitle":"zTest","folderUrl":"/dashboards/f/NUrBVPWmz/ztest","provisioned":false,"provisionedExternalId":"","annotationsPermissions":{"dashboard":{"canAdd":true,"canEdit":true,"canDelete":true},"organization":{"canAdd":false,"canEdit":false,"canDelete":false}},"hasPublicDashboard":false,"publicDashboardAccessToken":"","publicDashboardUid":"","publicDashboardEnabled":false},"dashboard":{"annotations":{"list":[{"builtIn":1,"datasource":"-- Grafana --","enable":true,"hide":true,"iconColor":"rgba(0, 211, 255, 1)","name":"Annotations \u0026 Alerts","type":"dashboard"}]},"editable":true,"gnetId":null,"graphTooltip":0,"hideControls":false,"id":931,"iteration":1603722220231,"links":[],"panels":[{"aliasColors":{},"bars":false,"dashLength":10,"dashes":false,"datasource":"Elastic Metrics","editable":true,"error":false,"fieldConfig":{"defaults":{"custom":{},"links":[]},"overrides":[]},"fill":1,"fillGradient":0,"grid":{},"gridPos":{"h":7,"w":24,"x":0,"y":0},"hiddenSeries":false,"id":1,"legend":{"alignAsTable":true,"avg":false,"current":false,"max":true,"min":false,"rightSide":true,"show":true,"total":false,"values":true},"lines":true,"linewidth":2,"links":[],"nullPointMode":"connected","options":{"alertThreshold":true},"paceLength":10,"percentage":false,"pluginVersion":"7.3.0-beta2","pointradius":5,"points":false,"renderer":"flot","seriesOverrides":[],"spaceLength":10,"stack":false,"steppedLine":false,"targets":[{"bucketAggs":[{"field":"@hostname","id":"3","settings":{"min_doc_count":1,"order":"asc","orderBy":"1","size":"5"},"type":"terms"},{"field":"@timestamp","id":"2","settings":{"interval":"auto","min_doc_count":0,"trimEdges":0},"type":"date_histogram"}],"dsType":"elasticsearch","metrics":[{"field":"@value","id":"1","meta":{},"settings":{},"type":"max"}],"query":"*","refId":"A","target":"","timeField":"@timestamp"}],"thresholds":[],"timeFrom":null,"timeRegions":[],"timeShift":null,"title":"Top 5 servers","tooltip":{"msResolution":true,"shared":true,"sort":0,"value_type":"cumulative"},"type":"graph","xaxis":{"buckets":null,"mode":"time","name":null,"show":true,"values":[]},"yaxes":[{"format":"short","logBase":1,"max":null,"min":null,"show":true},{"format":"short","logBase":1,"max":null,"min":null,"show":true}],"yaxis":{"align":false,"alignLevel":null}},{"aliasColors":{"Count":"#6ED0E0"},"bars":false,"dashLength":10,"dashes":false,"datasource":"Elastic Metrics","editable":true,"error":false,"fieldConfig":{"defaults":{"custom":{},"links":[]},"overrides":[]},"fill":1,"fillGradient":0,"grid":{},"gridPos":{"h":6,"w":12,"x":0,"y":7},"hiddenSeries":false,"id":2,"legend":{"alignAsTable":true,"avg":true,"current":false,"max":false,"min":false,"rightSide":true,"show":true,"total":false,"values":true},"lines":true,"linewidth":2,"links":[],"nullPointMode":"connected","options":{"alertThreshold":true},"paceLength":10,"percentage":false,"pluginVersion":"7.3.0-beta2","pointradius":5,"points":false,"renderer":"flot","seriesOverrides":[{"alias":"Count","lines":false,"yaxis":2,"zindex":-1}],"spaceLength":10,"stack":false,"steppedLine":false,"targets":[{"alias":"{{metric}}","bucketAggs":[{"field":"@timestamp","id":"2","settings":{"interval":"5m"},"type":"date_histogram"}],"dsType":"elasticsearch","metrics":[{"field":"@value","id":"1","meta":{},"settings":{"percents":[25,50,75,95,99]},"type":"percentiles"}],"query":"@metric:cpu","refId":"A","target":"","timeField":"@timestamp"}],"thresholds":[],"timeFrom":null,"timeRegions":[],"timeShift":null,"title":"Percentiles \u0026 Metric filter","tooltip":{"msResolution":false,"shared":true,"sort":0,"value_type":"cumulative"},"type":"graph","xaxis":{"buckets":null,"mode":"time","name":null,"show":true,"values":[]},"yaxes":[{"format":"short","logBase":1,"max":null,"min":null,"show":true},{"format":"short","logBase":1,"max":null,"min":null,"show":true}],"yaxis":{"align":false,"alignLevel":null}},{"aliasColors":{"Count":"#6ED0E0"},"bars":false,"dashLength":10,"dashes":false,"datasource":"Elastic Metrics","editable":true,"error":false,"fieldConfig":{"defaults":{"custom":{},"links":[]},"overrides":[]},"fill":1,"fillGradient":0,"grid":{},"gridPos":{"h":6,"w":12,"x":12,"y":7},"hiddenSeries":false,"id":3,"legend":{"alignAsTable":true,"avg":true,"current":false,"max":false,"min":false,"rightSide":true,"show":true,"total":false,"values":true},"lines":true,"linewidth":2,"links":[],"nullPointMode":"connected","options":{"alertThreshold":true},"paceLength":10,"percentage":false,"pluginVersion":"7.3.0-beta2","pointradius":5,"points":false,"renderer":"flot","seriesOverrides":[{"alias":"Count","lines":false,"yaxis":2,"zindex":-1}],"spaceLength":10,"stack":false,"steppedLine":false,"targets":[{"alias":"{{metric}}","bucketAggs":[{"field":"@timestamp","id":"2","settings":{"interval":"auto"},"type":"date_histogram"}],"dsType":"elasticsearch","metrics":[{"field":"@value","id":"1","meta":{"std_deviation_bounds_lower":true,"std_deviation_bounds_upper":true},"settings":{},"type":"extended_stats"}],"query":"@metric:cpu","refId":"A","target":"","timeField":"@timestamp"}],"thresholds":[],"timeFrom":null,"timeRegions":[],"timeShift":null,"title":"Standard dev","tooltip":{"msResolution":true,"shared":true,"sort":0,"value_type":"cumulative"},"type":"graph","xaxis":{"buckets":null,"mode":"time","name":null,"show":true,"values":[]},"yaxes":[{"format":"short","logBase":1,"max":null,"min":null,"show":true},{"format":"short","logBase":1,"max":null,"min":null,"show":true}],"yaxis":{"align":false,"alignLevel":null}},{"datasource":"Elastic Metrics","fieldConfig":{"defaults":{"custom":{"align":null,"filterable":false},"mappings":[],"thresholds":{"mode":"absolute","steps":[{"color":"green","value":null},{"color":"red","value":80}]}},"overrides":[{"matcher":{"id":"byName","options":"Sum"},"properties":[{"id":"custom.width","value":495}]}]},"gridPos":{"h":7,"w":12,"x":0,"y":13},"id":6,"links":[],"options":{"showHeader":true,"sortBy":[]},"pluginVersion":"7.3.0-beta2","targets":[{"bucketAggs":[{"$$hashKey":"object:434","field":"@hostname","id":"2","settings":{"min_doc_count":0,"order":"asc","orderBy":"_term","size":"0"},"type":"terms"}],"dsType":"elasticsearch","metrics":[{"$$hashKey":"object:428","field":"@value","id":"1","meta":{},"settings":{},"type":"avg"},{"$$hashKey":"object:429","field":"@value","id":"3","meta":{},"settings":{},"type":"max"},{"$$hashKey":"object:430","field":"@value","id":"4","meta":{},"settings":{},"type":"sum"}],"refId":"B","timeField":"@timestamp"}],"title":"ES Metrics","transformations":[{"id":"organize","options":{"excludeByName":{},"indexByName":{"@hostname":3,"Average":0,"Max":1,"Sum":2},"renameByName":{}}}],"type":"table"},{"datasource":"ES Logs","fieldConfig":{"defaults":{"custom":{"align":null,"filterable":false},"mappings":[],"thresholds":{"mode":"absolute","steps":[{"color":"green","value":null},{"color":"red","value":80}]}},"overrides":[]},"gridPos":{"h":7,"w":24,"x":0,"y":20},"id":5,"links":[],"options":{"showHeader":true},"pluginVersion":"7.3.0-beta2","targets":[{"bucketAggs":[],"dsType":"elasticsearch","metrics":[{"$$hashKey":"object:544","field":"select field","id":"1","meta":{},"settings":{"size":500},"type":"raw_data"}],"refId":"A","target":"","timeField":"@timestamp"}],"title":"ES Log query","transformations":[{"id":"organize","options":{"excludeByName":{"_id":true,"_index":true,"_type":true,"coordinates.latitude":true,"coordinates.level.coolnes":true,"coordinates.level.depth":true,"coordinates.longitude":true,"unescaped-content":true},"indexByName":{},"renameByName":{}}}],"type":"table"}],"schemaVersion":26,"style":"dark","tags":[],"templating":{"list":[{"datasource":"Elastic Metrics","error":null,"filters":[],"hide":0,"label":"","name":"Filters","skipUrlSync":false,"type":"adhoc"},{"allValue":null,"current":{"selected":false,"text":"1","value":"1"},"error":null,"hide":0,"includeAll":false,"label":null,"multi":false,"name":"NewFilter","options":[{"selected":true,"text":"1","value":"1"},{"selected":false,"text":"2","value":"2"},{"selected":false,"text":"3","value":"3"},{"selected":false,"text":"5","value":"5"},{"selected":false,"text":"10","value":"10"}],"query":"1,2,3,5,10","skipUrlSync":false,"type":"custom"}]},"time":{"from":"now-30m","to":"now"},"timepicker":{"collapse":false,"enable":true,"notice":false,"now":true,"refresh_intervals":["5s","10s","30s","1m","5m","15m","30m","1h","2h","1d"],"status":"Stable","time_options":["5m","15m","1h","6h","12h","24h","2d","7d","30d"],"type":"timepicker"},"timezone":"browser","title":"Elasticsearch Metrics Copy","uid":"HpOzpLpMz","version":1}}