{"meta":{"type":"db","canSave":false,"canEdit":true,"canAdmin":false,"canStar":false,"canDelete":false,"slug":"contract-numericlong","url":"/d/O8FmVgH4k/contract-numericlong","expires":"0001-01-01T00:00:00Z","created":"2022-10-31T13:30:06Z","updated":"2022-10-31T13:30:06Z","updatedBy":"kyle@grafana.com","createdBy":"kyle@grafana.com","version":1,"hasAcl":false,"isFolder":false,"folderId":1641,"folderUid":"2NNsFbHVz","folderTitle":"Data Plane","folderUrl":"/dashboards/f/2NNsFbHVz/data-plane","provisioned":false,"provisionedExternalId":"","annotationsPermissions":{"dashboard":{"canAdd":true,"canEdit":true,"canDelete":true},"organization":{"canAdd":false,"canEdit":false,"canDelete":false}},"hasPublicDashboard":false,"publicDashboardAccessToken":"","publicDashboardUid":"","publicDashboardEnabled":false},"dashboard":{"annotations":{"list":[{"builtIn":1,"datasource":{"type":"grafana","uid":"-- Grafana --"},"enable":true,"hide":true,"iconColor":"rgba(0, 211, 255, 1)","name":"Annotations \u0026 Alerts","target":{"limit":100,"matchAny":false,"tags":[],"type":"dashboard"},"type":"dashboard"}]},"editable":true,"fiscalYearStartMonth":0,"graphTooltip":0,"id":1646,"links":[],"liveNow":false,"panels":[{"gridPos":{"h":1,"w":24,"x":0,"y":0},"id":2,"title":"NoData \u0026 Empty","type":"row"},{"datasource":{"type":"grafana-mock-datasource","uid":"3QPj-dNVk"},"fieldConfig":{"defaults":{"color":{"mode":"thresholds"},"custom":{"align":"auto","displayMode":"auto","inspect":false},"mappings":[],"thresholds":{"mode":"absolute","steps":[{"color":"green","value":null},{"color":"red","value":80}]}},"overrides":[]},"gridPos":{"h":5,"w":12,"x":0,"y":1},"id":4,"options":{"footer":{"fields":"","reducer":["sum"],"show":false},"showHeader":true},"pluginVersion":"9.3.0-pre","targets":[{"datasource":{"type":"grafana-mock-datasource","uid":"3QPj-dNVk"},"generatorSource":"backend","queryType":"raw_frame","rawFrameContent":"[\n  {\n    \"schema\": {\n      \"meta\": {\n        \"type\": \"numeric-long\"\n      },\n      \"fields\": []\n    },\n    \"data\": {\n      \"values\": []\n    }\n  }\n]","rawFrameSource":"inline","refId":"A","resultState":"success","scenario":"no-data"}],"title":"NumericLong: No Data","type":"table"},{"datasource":{"type":"grafana-mock-datasource","uid":"3QPj-dNVk"},"fieldConfig":{"defaults":{"color":{"mode":"thresholds"},"custom":{"align":"auto","displayMode":"auto","inspect":false},"mappings":[],"thresholds":{"mode":"absolute","steps":[{"color":"green","value":null},{"color":"red","value":80}]}},"overrides":[]},"gridPos":{"h":5,"w":12,"x":12,"y":1},"id":5,"options":{"footer":{"fields":"","reducer":["sum"],"show":false},"showHeader":true},"pluginVersion":"9.3.0-pre","targets":[{"datasource":{"type":"grafana-mock-datasource","uid":"3QPj-dNVk"},"generatorSource":"backend","queryType":"raw_frame","rawFrameContent":"[\n  {\n    \"schema\": {\n      \"meta\": {\n        \"type\": \"numeric-long\"\n      },\n      \"fields\": [\n        {\n          \"type\": \"number\",\n          \"name\": \"avgSlothCount\",\n          \"typeInfo\": {\n            \"frame\": \"float64\"\n          }\n        },\n        {\n          \"type\": \"number\",\n          \"name\": \"avgSleepHoursPerSlothPerDay\",\n          \"typeInfo\": {\n            \"frame\": \"float64\"\n          }\n        },\n        {\n            \"type\": \"string\",\n            \"name\": \"city\",\n            \"typeInfo\": {\n              \"frame\": \"string\"\n            }\n        }\n      ]\n    },\n    \"data\": {\n      \"values\": []\n    }\n  }\n]","rawFrameSource":"inline","refId":"A","resultState":"success","scenario":"no-data"}],"title":"NumericLong: Empty","type":"table"},{"collapsed":false,"gridPos":{"h":1,"w":24,"x":0,"y":6},"id":7,"panels":[],"title":"Two Items","type":"row"},{"datasource":{"type":"grafana-mock-datasource","uid":"3QPj-dNVk"},"description":"","fieldConfig":{"defaults":{"color":{"mode":"thresholds"},"custom":{"align":"auto","displayMode":"auto","inspect":false},"mappings":[],"thresholds":{"mode":"absolute","steps":[{"color":"green","value":null},{"color":"red","value":80}]}},"overrides":[]},"gridPos":{"h":5,"w":12,"x":0,"y":7},"id":8,"options":{"footer":{"fields":"","reducer":["sum"],"show":false},"showHeader":true},"pluginVersion":"9.3.0-pre","targets":[{"datasource":{"type":"grafana-mock-datasource","uid":"3QPj-dNVk"},"generatorSource":"backend","queryType":"raw_frame","rawFrameContent":"[\n  {\n    \"schema\": {\n      \"meta\": {\n        \"type\": \"numeric-long\"\n      },\n      \"fields\": [\n        {\n          \"type\": \"number\",\n          \"name\": \"avgSlothCount\",\n          \"typeInfo\": {\n            \"frame\": \"float64\"\n          }\n        },\n        {\n            \"type\": \"string\",\n            \"name\": \"city\",\n            \"typeInfo\": {\n              \"frame\": \"string\"\n            }\n        }\n      ]\n    },\n    \"data\": {\n      \"values\": [\n        [4, 7.5],\n        [\"LGA\", \"MIA\"]\n      ]\n    }\n  }\n]","rawFrameSource":"inline","refId":"A","resultState":"success","scenario":"no-data"}],"title":"NumericLong: Two Items By Dimension","type":"table"},{"datasource":{"type":"grafana-mock-datasource","uid":"3QPj-dNVk"},"description":"","fieldConfig":{"defaults":{"color":{"mode":"thresholds"},"custom":{"align":"auto","displayMode":"auto","inspect":false},"mappings":[],"thresholds":{"mode":"absolute","steps":[{"color":"green","value":null},{"color":"red","value":80}]}},"overrides":[]},"gridPos":{"h":5,"w":12,"x":12,"y":7},"id":9,"options":{"footer":{"fields":"","reducer":["sum"],"show":false},"showHeader":true},"pluginVersion":"9.3.0-pre","targets":[{"datasource":{"type":"grafana-mock-datasource","uid":"3QPj-dNVk"},"generatorSource":"backend","queryType":"raw_frame","rawFrameContent":"[\n  {\n    \"schema\": {\n      \"meta\": {\n        \"type\": \"numeric-long\"\n      },\n      \"fields\": [\n        {\n          \"type\": \"number\",\n          \"name\": \"avgSlothCount\",\n          \"typeInfo\": {\n            \"frame\": \"float64\"\n          }\n        },\n        {\n          \"type\": \"number\",\n          \"name\": \"avgSleepHoursPerSlothPerDay\",\n          \"typeInfo\": {\n            \"frame\": \"float64\"\n          }\n        },\n        {\n          \"type\": \"string\",\n          \"name\": \"city\",\n          \"typeInfo\": {\n            \"frame\": \"string\"\n          }\n        }\n      ]\n    },\n    \"data\": {\n      \"values\": [\n        [4, 7.5],\n        [23.5, 23.2],\n        [\"LGA\", \"MIA\"]\n      ]\n    }\n  }\n]\n","rawFrameSource":"inline","refId":"A","resultState":"success","scenario":"no-data"}],"title":"NumericLong: Four Items By Name \u0026 Dimension","type":"table"},{"collapsed":false,"gridPos":{"h":1,"w":24,"x":0,"y":12},"id":11,"panels":[],"title":"Four Items","type":"row"},{"datasource":{"type":"grafana-mock-datasource","uid":"3QPj-dNVk"},"description":"","fieldConfig":{"defaults":{"color":{"mode":"thresholds"},"custom":{"align":"auto","displayMode":"auto","inspect":false},"mappings":[],"thresholds":{"mode":"absolute","steps":[{"color":"green","value":null},{"color":"red","value":80}]}},"overrides":[]},"gridPos":{"h":5,"w":12,"x":0,"y":13},"id":12,"options":{"footer":{"fields":"","reducer":["sum"],"show":false},"showHeader":true},"pluginVersion":"9.3.0-pre","targets":[{"datasource":{"type":"grafana-mock-datasource","uid":"3QPj-dNVk"},"generatorSource":"backend","queryType":"raw_frame","rawFrameContent":"[\n  {\n    \"schema\": {\n      \"meta\": {\n        \"type\": \"numeric-long\"\n      },\n      \"fields\": [\n        {\n          \"type\": \"number\",\n          \"name\": \"avgSlothCount\",\n          \"typeInfo\": {\n            \"frame\": \"float64\"\n          }\n        },\n        {\n          \"type\": \"number\",\n          \"name\": \"avgSleepHoursPerSlothPerDay\",\n          \"typeInfo\": {\n            \"frame\": \"float64\"\n          }\n        },\n        {\n          \"type\": \"string\",\n          \"name\": \"city\",\n          \"typeInfo\": {\n            \"frame\": \"string\"\n          }\n        }\n      ]\n    },\n    \"data\": {\n      \"values\": [\n        [4, 7.5],\n        [23.5, 23.2],\n        [\"LGA\", \"MIA\"]\n      ]\n    }\n  }\n]\n","rawFrameSource":"inline","refId":"A","resultState":"success","scenario":"no-data"}],"title":"NumericLong: Four Items By Name \u0026 Dimension","type":"table"}],"schemaVersion":37,"style":"dark","tags":[],"templating":{"list":[]},"time":{"from":"now-6h","to":"now"},"timepicker":{},"timezone":"","title":"Contract: NumericLong","uid":"O8FmVgH4k","version":1,"weekStart":""}}