{"meta":{"type":"db","canSave":false,"canEdit":true,"canAdmin":false,"canStar":false,"canDelete":false,"slug":"38424-annotations-panel-does-not-show-annotations-end-time-if-present","url":"/d/rooljXnnk/38424-annotations-panel-does-not-show-annotations-end-time-if-present","expires":"0001-01-01T00:00:00Z","created":"2021-08-23T09:30:47Z","updated":"2021-08-23T09:35:29Z","updatedBy":"alexandra.vargas@grafana.com","createdBy":"alexandra.vargas@grafana.com","version":5,"hasAcl":false,"isFolder":false,"folderId":1113,"folderUid":"8OticeRnk","folderTitle":"Replicating issues","folderUrl":"/dashboards/f/8OticeRnk/replicating-issues","provisioned":false,"provisionedExternalId":"","annotationsPermissions":{"dashboard":{"canAdd":true,"canEdit":true,"canDelete":true},"organization":{"canAdd":false,"canEdit":false,"canDelete":false}},"hasPublicDashboard":false,"publicDashboardAccessToken":"","publicDashboardUid":"","publicDashboardEnabled":false},"dashboard":{"annotations":{"list":[{"builtIn":1,"datasource":"-- Grafana --","enable":true,"hide":false,"iconColor":"rgba(0, 211, 255, 1)","name":"Annotations \u0026 Alerts","target":{"limit":100,"matchAny":false,"tags":[],"type":"dashboard"},"type":"dashboard"}]},"editable":true,"gnetId":null,"graphTooltip":0,"id":1180,"links":[],"panels":[{"datasource":"TestData DB","gridPos":{"h":8,"w":12,"x":0,"y":0},"id":4,"options":{"angular":{"limit":10,"navigateAfter":"10m","navigateBefore":"10m","navigateToPanel":true,"onlyFromThisDashboard":false,"options":{},"showTags":true,"showTime":true,"showUser":true,"tags":[]},"limit":10,"navigateAfter":"10m","navigateBefore":"10m","onlyFromThisDashboard":true,"onlyInTimeRange":false,"showTags":true,"showTime":true,"showUser":true},"title":"Panel Title","type":"annolist"},{"datasource":"TestData DB","fieldConfig":{"defaults":{"color":{"mode":"palette-classic"},"custom":{"axisLabel":"","axisPlacement":"auto","barAlignment":0,"drawStyle":"line","fillOpacity":0,"gradientMode":"none","hideFrom":{"legend":false,"tooltip":false,"viz":false},"lineInterpolation":"linear","lineWidth":1,"pointSize":5,"scaleDistribution":{"type":"linear"},"showPoints":"auto","spanNulls":false,"stacking":{"group":"A","mode":"none"},"thresholdsStyle":{"mode":"off"}},"mappings":[],"thresholds":{"mode":"absolute","steps":[{"color":"green","value":null},{"color":"red","value":80}]}},"overrides":[]},"gridPos":{"h":9,"w":12,"x":0,"y":8},"id":2,"options":{"legend":{"calcs":[],"displayMode":"list","placement":"bottom"},"tooltip":{"mode":"single"}},"title":"Panel Title","type":"timeseries"}],"refresh":false,"schemaVersion":30,"style":"dark","tags":[],"templating":{"list":[]},"time":{"from":"2021-08-23T09:10:12.020Z","to":"2021-08-23T09:12:01.804Z"},"timepicker":{},"timezone":"","title":"38424: Annotations Panel: Does not show annotations end time if present","uid":"rooljXnnk","version":5}}